pymicra/__init__.py
pymicra/constants.py
pymicra/core.py
pymicra/decorators.py
pymicra/io.py
pymicra/methods.py
pymicra/physics.py
pymicra/pymicra.pint
pymicra/tests.py
pymicra/util.py
pymicra/version
pymicra/algs/__init__.py
pymicra/algs/auxiliar.py
pymicra/algs/general.py
pymicra/algs/numeric.py
pymicra/algs/units.py
pymicra/micro/__init__.py
pymicra/micro/functions.py
pymicra/micro/scales.py
pymicra/micro/spectral.py
pymicra/micro/util.py
pymicra/signal/__init__.py
pymicra/signal/csignal.py
pymicra/signal/pysignal.py
pymicra-0.4.1.dist-info/DESCRIPTION.rst
pymicra-0.4.1.dist-info/METADATA
pymicra-0.4.1.dist-info/RECORD
pymicra-0.4.1.dist-info/WHEEL
pymicra-0.4.1.dist-info/metadata.json
pymicra-0.4.1.dist-info/top_level.txt
