Metadata-Version: 2.0
Name: pymicra
Version: 0.4.1
Summary: A Python tool for Micrometeorological Analyses
Home-page: https://github.com/tomchor/pymicra.git
Author: Tomas Chor
Author-email: tomaschor@gmail.com
License: GNU GPL V3.0
Keywords: meteorology,micrometeorology,atmosphere,science
Platform: UNKNOWN
Requires-Dist: Pandas
Requires-Dist: Numpy
Requires-Dist: pint
